{
  "indexes": [
    {
      "collectionGroup": "specbook_items",
      "queryScope": "COLLECTION",
      "fields": [
        { "fieldPath": "is_library", "order": "ASCENDING" },
        { "fieldPath": "category", "order": "ASCENDING" },
        { "fieldPath": "name", "order": "ASCENDING" }
      ]
    },
    {
      "collectionGroup": "specbook_items",
      "queryScope": "COLLECTION",
      "fields": [
        { "fieldPath": "is_library", "order": "ASCENDING" },
        { "fieldPath": "name", "order": "ASCENDING" }
      ]
    },
    {
      "collectionGroup": "specbook_items",
      "queryScope": "COLLECTION",
      "fields": [
        { "fieldPath": "project_id", "order": "ASCENDING" },
        { "fieldPath": "category", "order": "ASCENDING" },
        { "fieldPath": "name", "order": "ASCENDING" }
      ]
    },
    {
      "collectionGroup": "execution_records",
      "queryScope": "COLLECTION",
      "fields": [
        { "fieldPath": "project", "order": "ASCENDING" },
        { "fieldPath": "createdAt", "order": "DESCENDING" }
      ]
    },
    {
      "collectionGroup": "work_requests",
      "queryScope": "COLLECTION",
      "fields": [
        { "fieldPath": "project", "order": "ASCENDING" },
        { "fieldPath": "createdAt", "order": "DESCENDING" }
      ]
    },
    {
      "collectionGroup": "payments",
      "queryScope": "COLLECTION",
      "fields": [
        { "fieldPath": "project", "order": "ASCENDING" },
        { "fieldPath": "createdAt", "order": "DESCENDING" }
      ]
    }
  ],
  "fieldOverrides": []
}
